{"77478765580@s.whatsapp.net":true,"77057261089@s.whatsapp.net":true,"77054118307@s.whatsapp.net":true,"77074339635@s.whatsapp.net":true,"77756954241@s.whatsapp.net":true,"77474537603@s.whatsapp.net":true,"77770403906@s.whatsapp.net":true,"77055830164@s.whatsapp.net":true,"77056419936@s.whatsapp.net":true,"77775953515@s.whatsapp.net":true,"77025364518@s.whatsapp.net":true,"77002772073@s.whatsapp.net":true,"77476318003@s.whatsapp.net":true,"77026622277@s.whatsapp.net":true,"77051420957@s.whatsapp.net":true,"77052529412@s.whatsapp.net":true,"77785246525@s.whatsapp.net":true,"77754314758@s.whatsapp.net":true,"77759173120@s.whatsapp.net":true,"77752430420@s.whatsapp.net":true,"77771528590@s.whatsapp.net":true,"77051732388@s.whatsapp.net":true,"77058462205@s.whatsapp.net":true,"77710377357@s.whatsapp.net":true,"77055576929@s.whatsapp.net":true,"77028348249@s.whatsapp.net":true,"77712456869@s.whatsapp.net":true,"77787381328@s.whatsapp.net":true,"77750545935@s.whatsapp.net":true,"77779920081@s.whatsapp.net":true,"77073696020@s.whatsapp.net":true,"77053389636@s.whatsapp.net":true,"6282156746964@s.whatsapp.net":true,"77054092209@s.whatsapp.net":true,"77051242811@s.whatsapp.net":true,"77768296385@s.whatsapp.net":true,"77712683853@s.whatsapp.net":true,"77058743646@s.whatsapp.net":true,"77713996249@s.whatsapp.net":true,"77479253009@s.whatsapp.net":true,"77076369361@s.whatsapp.net":true,"77055996103@s.whatsapp.net":true,"77711666723@s.whatsapp.net":true,"77780203195@s.whatsapp.net":true,"77057207255@s.whatsapp.net":true,"77475574731@s.whatsapp.net":true,"639109286712@s.whatsapp.net":true,"77000930293@s.whatsapp.net":true,"77471290578@s.whatsapp.net":true,"77474145958@s.whatsapp.net":true,"77025712626@s.whatsapp.net":true,"77474961143@s.whatsapp.net":true,"77053627228@s.whatsapp.net":true,"77054252943@s.whatsapp.net":true,"77055253861@s.whatsapp.net":true,"77058933817@s.whatsapp.net":true,"77470258906@s.whatsapp.net":true,"77052424116@s.whatsapp.net":true,"77765877077@s.whatsapp.net":true,"77051854308@s.whatsapp.net":true,"77059522009@s.whatsapp.net":true,"77075488489@s.whatsapp.net":true,"77075909721@s.whatsapp.net":true,"77751548045@s.whatsapp.net":true,"77476160479@s.whatsapp.net":true,"77076154048@s.whatsapp.net":true,"77753345612@s.whatsapp.net":true,"77075607310@s.whatsapp.net":true,"77074112573@s.whatsapp.net":true,"77711480738@s.whatsapp.net":true,"77054956085@s.whatsapp.net":true,"77714285297@s.whatsapp.net":true,"77757948011@s.whatsapp.net":true,"77059701772@s.whatsapp.net":true,"77760058118@s.whatsapp.net":true,"77057178560@s.whatsapp.net":true,"77476176718@s.whatsapp.net":true,"77079206324@s.whatsapp.net":true,"77712850399@s.whatsapp.net":true,"77051349259@s.whatsapp.net":true,"77711520588@s.whatsapp.net":true,"77009781634@s.whatsapp.net":true,"77053616974@s.whatsapp.net":true,"77778387709@s.whatsapp.net":true,"77470965906@s.whatsapp.net":true,"77479846454@s.whatsapp.net":true,"77714194393@s.whatsapp.net":true,"77475541794@s.whatsapp.net":true,"77476559347@s.whatsapp.net":true,"77476559347:1@s.whatsapp.net":true,"77476559347:2@s.whatsapp.net":true,"77753129591@s.whatsapp.net":true,"77473941933@s.whatsapp.net":true}